<?xml version="1.0" encoding="UTF-8"?>
<objects serializationModel="Studio.02.00.00">
	<object class="AudioFile" id="{1be0d69c-74b4-43a1-b198-e5e732108641}">
		<property name="assetPath">
			<value>stone-collision-001.wav</value>
		</property>
		<property name="frequencyInKHz">
			<value>44.0999985</value>
		</property>
		<property name="channelCount">
			<value>2</value>
		</property>
		<property name="length">
			<value>0.18922902494331065</value>
		</property>
		<relationship name="masterAssetFolder">
			<destination>{6034d70e-93f3-4385-a722-ea7896803a12}</destination>
		</relationship>
	</object>
</objects>
